analyze_objects/__init__.py
analyze_objects/config.py
analyze_objects/find_symbols.py
analyze_objects/object_analyzer.py
analyze_objects/print_colored.py
analyze_objects-0.3.0.dist-info/LICENSE.txt
analyze_objects-0.3.0.dist-info/METADATA
analyze_objects-0.3.0.dist-info/WHEEL
analyze_objects-0.3.0.dist-info/entry_points.txt
analyze_objects-0.3.0.dist-info/top_level.txt
analyze_objects-0.3.0.dist-info/RECORD
