Metadata-Version: 2.1
Name: analyze-objects
Version: 0.3.0
Summary: Contains command line tools and python functions to search symbols in object files (.o, .obj).
Home-page: https://gitlab.com/pschill/analyze_objects
Author: Philip Schill
Author-email: philip.schill@gmx.de
License: UNKNOWN
Platform: UNKNOWN
Classifier: Programming Language :: Python :: 3.6
Classifier: Programming Language :: Python :: 3.7
Classifier: License :: OSI Approved :: MIT License
Classifier: Operating System :: Microsoft :: Windows
Classifier: Operating System :: POSIX :: Linux
Classifier: Topic :: Software Development
Classifier: Topic :: Utilities
Requires-Python: >=3.6
Requires-Dist: appdirs
Requires-Dist: colorama
